mpcaHydro/__init__.py
mpcaHydro/data_manager.py
mpcaHydro/equis.py
mpcaHydro/etlCSG.py
mpcaHydro/etlSWD.py
mpcaHydro/etlWISKI.py
mpcaHydro/etlWPLMN.py
mpcaHydro/outlets.py
mpcaHydro/pywisk.py
mpcaHydro/reports.py
mpcaHydro/warehouse.py
mpcaHydro/warehouseManager.py
mpcaHydro/wiski.py
mpcaHydro/xref.py
mpcaHydro/data/EQUIS_PARAMETER_XREF.csv
mpcaHydro/data/WISKI_EQUIS_XREF.csv
mpcaHydro/data/WISKI_QUALITY_CODES.csv
mpcaHydro/data/outlet.duckdb
mpcaHydro/data/stations_EQUIS.gpkg
mpcaHydro/data/stations_wiski.gpkg
mpcaHydro/data/stations_wiski.gpkg-shm
mpcaHydro/data/stations_wiski.gpkg-wal
mpcahydro-2.2.2.dist-info/METADATA
mpcahydro-2.2.2.dist-info/WHEEL
mpcahydro-2.2.2.dist-info/RECORD
