Metadata-Version: 2.4
Name: mpcaHydro
Version: 2.2.2
Summary: Python package for downloading MPCA hydrology data
Project-URL: Homepage, https://github.com/mfratkin1/mpcaHydro
Author-email: Mulu Fratkin <michael.fratkin@state.mn.us>
Maintainer-email: Mulu Fratkin <michael.fratkin@state.mn.us>
License-Expression: MIT
Keywords: Hydrology,MPCA
Classifier: Development Status :: 3 - Alpha
Classifier: Programming Language :: Python
Requires-Python: >=3.8
Requires-Dist: baseflow
Requires-Dist: duckdb
Requires-Dist: oracledb
Requires-Dist: pandas
Requires-Dist: pathlib
Requires-Dist: requests
